datadict_toolbox/__init__.py
datadict_toolbox/extract_from_dtsx.py
datadict_toolbox/extract_from_sql_query.py
datadict_toolbox/extract_from_xmla.py
datadict_toolbox/select_gpt_deduce.py
datadict_toolbox/usefull.py
datadict_toolbox-1.0.1.dist-info/LICENSE
datadict_toolbox-1.0.1.dist-info/METADATA
datadict_toolbox-1.0.1.dist-info/WHEEL
datadict_toolbox-1.0.1.dist-info/top_level.txt
datadict_toolbox-1.0.1.dist-info/RECORD
