Metadata-Version: 2.1
Name: datadict-toolbox
Version: 1.0.1
Summary: A package to build a data dictionary from .xmla MS SQL SERVER file and select SQL query.
Home-page: https://github.com/LauNop/datadict-toolbox
Author: Laurent NOPOLY
Author-email: laurentnopoly@gmail.com
License: MIT
Keywords: python,data,dictionary,governance,SQL
Classifier: Development Status :: 7 - Inactive
Classifier: Intended Audience :: Developers
Classifier: Programming Language :: Python :: 3
Classifier: Operating System :: Microsoft :: Windows
License-File: LICENSE
Requires-Dist: openai
Requires-Dist: pandas
Requires-Dist: openpyxl
Requires-Dist: python-dotenv
